{"type":"Topology","arcs":[[[2009,1275],[-226,-176],[-172,-131],[-65,-102],[-31,-55],[-101,-165],[-193,-305],[-93,-145],[-101,-196],[-69,128],[-223,139],[-383,235]],[[352,502],[105,420],[33,148],[70,333],[69,299],[35,129],[17,31],[33,20],[52,14],[46,-5],[44,-13],[13,-11],[17,-37],[-11,-56],[10,-52],[6,-6],[238,51],[45,-24],[203,-113],[381,-217],[243,-133],[8,-5]],[[352,502],[0,-2],[-335,211],[-17,28],[3,39],[80,311],[89,334],[90,345],[36,144],[-1,5],[44,135],[27,52],[180,349],[125,239],[38,67],[205,333],[22,30],[197,-167],[31,-20],[24,-9],[143,-40],[103,-49],[54,-8],[19,-20],[42,-30],[14,-19],[24,-8],[10,-17]],[[1599,2735],[-1,-25],[9,-11],[97,-53],[17,31]],[[1721,2677],[213,-101],[235,-107],[299,-141],[308,-147],[-3,-38],[-17,-112],[-20,-196],[-1,-8],[-223,-161],[-13,-15],[-466,-360],[-24,-16]],[[1155,2813],[-1,-18],[47,-45],[20,27],[-28,30],[-16,26],[-11,33],[-21,-35],[10,-18]],[[1599,2735],[2,0],[120,-58]]],"transform":{"scale":[28.965766618579156,29.89111762256133],"translate":[8218658.688014663,1281714.192187026]},"objects":{"lcsd000a25a_e":{"type":"GeometryCollection","geometries":[{"arcs":[[0,1]],"type":"Polygon","properties":{"PRUID":"12","PRNAME":"Nova Scotia / Nouvelle-Écosse","CDUID":"1203","CDNAME":"Digby","CDTYPE":"CTY","CSDUID":"1203001","CSDNAME":"Clare","CSDTYPE":"MD"}},{"arcs":[[-2,2,3,4],[5]],"type":"Polygon","properties":{"PRUID":"12","PRNAME":"Nova Scotia / Nouvelle-Écosse","CDUID":"1203","CDNAME":"Digby","CDTYPE":"CTY","CSDUID":"1203004","CSDNAME":"Digby","CSDTYPE":"MD"}},{"arcs":[[-6]],"type":"Polygon","properties":{"PRUID":"12","PRNAME":"Nova Scotia / Nouvelle-Écosse","CDUID":"1203","CDNAME":"Digby","CDTYPE":"CTY","CSDUID":"1203006","CSDNAME":"Digby","CSDTYPE":"T"}},{"arcs":[[-4,6]],"type":"Polygon","properties":{"PRUID":"12","PRNAME":"Nova Scotia / Nouvelle-Écosse","CDUID":"1203","CDNAME":"Digby","CDTYPE":"CTY","CSDUID":"1203009","CSDNAME":"Bear River (Part) 6","CSDTYPE":"IRI"}}]}}}